anujstick/__init__.py
anujstick/advanced_gui.py
anujstick/gui_app.py
anujstick/main.py
anujstick/core/__init__.py
anujstick/core/brute_force.py
anujstick/core/network_attacks.py
anujstick/core/web_exploits.py
anujstick-0.1.3.dist-info/licenses/LICENSE
anujstick-0.1.3.dist-info/METADATA
anujstick-0.1.3.dist-info/WHEEL
anujstick-0.1.3.dist-info/entry_points.txt
anujstick-0.1.3.dist-info/top_level.txt
anujstick-0.1.3.dist-info/RECORD
